LICENSE
README.md
setup.py
xcaliber_webhooks/XcaliberWebhook.py
xcaliber_webhooks/__init__.py
xcaliber_webhooks.egg-info/PKG-INFO
xcaliber_webhooks.egg-info/SOURCES.txt
xcaliber_webhooks.egg-info/dependency_links.txt
xcaliber_webhooks.egg-info/requires.txt
xcaliber_webhooks.egg-info/top_level.txt