Metadata-Version: 2.1
Name: xcaliber-webhooks
Version: 0.0.3
Summary: Xcaliber Webhooks
Keywords: xcaliber,webhooks
Classifier: Intended Audience :: Developers
Classifier: Programming Language :: Python :: 3
Classifier: Operating System :: Unix
Classifier: Operating System :: MacOS :: MacOS X
Classifier: Operating System :: Microsoft :: Windows
License-File: LICENSE
